{
  "name": "DL Templates (Torch on AMD/ROCm)",
  "dockerComposeFile": ["${localWorkspaceFolder}/docker-compose.yaml"],
  "service": "torch-amd",
  "runServices": ["torch-amd"],
  "workspaceFolder": "/workspace",
  "updateRemoteUserUID": true,
  "shutdownAction": "none",
  "overrideCommand": false,
  "customizations": {
    "vscode": {
      "extensions": [
        "ms-python.python",
        "ms-python.vscode-pylance",
        "ms-toolsai.jupyter",
        "ms-azuretools.vscode-docker"
      ]
    }
  }
}
